zensols/propbankdb/resources/app.conf
zensols/propbankdb/resources/default.conf
zensols/propbankdb/resources/embed.yml
zensols/propbankdb/resources/frameset.sql
zensols/propbankdb/resources/function.csv
zensols/propbankdb/resources/obj.yml
zensols/propbankdb/__init__.py
zensols/propbankdb/app.py
zensols/propbankdb/cli.py
zensols/propbankdb/dapp.py
zensols/propbankdb/db.py
zensols/propbankdb/domain.py
zensols/propbankdb/embedgen.py
zensols/propbankdb/embedpop.py
zensols/propbankdb/load.py
zensols/propbankdb/pack.py
zensols_propbankdb-0.2.1.dist-info/METADATA
zensols_propbankdb-0.2.1.dist-info/WHEEL
zensols_propbankdb-0.2.1.dist-info/entry_points.txt
zensols_propbankdb-0.2.1.dist-info/licenses/LICENSE.md
zensols_propbankdb-0.2.1.dist-info/RECORD
