Metadata-Version: 2.3
Name: zensols_propbankdb
Version: 0.2.1
Summary: An API to access PropBank data and generate embeddings from the paper "CALAMR: Component ALignment for Abstract Meaning Representation".
Project-URL: Homepage, https://github.com/plandes/propbankdb
Project-URL: Documentation, https://plandes.github.io/propbankdb
Project-URL: Repository, https://github.com/plandes/propbankdb.git
Project-URL: Issues, https://github.com/plandes/propbankdb/issues
Project-URL: Changelog, https://github.com/plandes/propbankdb/blob/master/CHANGELOG.md
Author-email: Paul Landes <landes@mailc.net>
License: MIT
Keywords: PropBank,abstract meaning representation,natural language processing
Requires-Python: <3.13,>=3.11
Requires-Dist: lxml~=4.9.3
Requires-Dist: penman~=1.3.0
Requires-Dist: zensols-db~=1.4.1
Requires-Dist: zensols-deepnlp~=1.18.1
